dd_dm/__init__.py
dd_dm/__main__.py
dd_dm/cli.py
dd_dm/commands/__init__.py
dd_dm/commands/add.py
dd_dm/commands/create.py
dd_dm/commands/init.py
dd_dm/commands/list.py
dd_dm/commands/remove.py
dd_dm/commands/update.py
dd_dm/core/__init__.py
dd_dm/core/config.py
dd_dm/core/constitution.py
dd_dm/core/exceptions.py
dd_dm/core/git_ops.py
dd_dm/core/module_manager.py
dd_dm/models/__init__.py
dd_dm/models/config.py
dd_dm/models/module.py
dd_dm/templates/AGENTS.md
dd_dm/templates/CLAUDE.md
dd_dm/templates/CONSTITUTION.md
dd_dm/templates/__init__.py
dd_dm/templates/modules/GIT_ATOMIC_COMMITS.md
dd_dm/templates/modules/GIT_CONVENTIONAL_COMMITS.md
dd_dm/templates/modules/__init__.py
dd_dm/utils/__init__.py
dd_dm/utils/console.py
dd_dm/utils/paths.py
dd_dungeonmaster-0.2.1.dist-info/METADATA
dd_dungeonmaster-0.2.1.dist-info/WHEEL
dd_dungeonmaster-0.2.1.dist-info/entry_points.txt
dd_dungeonmaster-0.2.1.dist-info/RECORD
